{
  "66d5294bb2732bbf0d7f51b3": {
    "$type": "RealismMod.Consumable, RealismMod",
    "Name": "Four Loko Watermelon",
    "TemplateType": "consumable",
    "LoyaltyLevel": 1,
    "BasePriceModifier": 1,
    "ConsumableType": "other",
    "Duration": 0,
    "Delay": 0,
    "EffectPeriod": 0,
    "WaitPeriod": 0,
    "Strength": 0,
    "TunnelVisionStrength": 0,
    "CanBeUsedInRaid": true,
    "ItemID": "66d5294bb2732bbf0d7f51b3"
  },
  "66d670424a66c0453ce2b2e0": {
    "$type": "RealismMod.Consumable, RealismMod",
    "Name": "Blue Mountain Four Loko",
    "TemplateType": "consumable",
    "LoyaltyLevel": 1,
    "BasePriceModifier": 1,
    "ConsumableType": "other",
    "Duration": 0,
    "Delay": 0,
    "EffectPeriod": 0,
    "WaitPeriod": 0,
    "Strength": 0,
    "TunnelVisionStrength": 0,
    "CanBeUsedInRaid": true,
    "ItemID": "66d670424a66c0453ce2b2e0"
  },
  "66d6708ae974feef81150037": {
    "$type": "RealismMod.Consumable, RealismMod",
    "Name": "Orange Four Loko",
    "TemplateType": "consumable",
    "LoyaltyLevel": 1,
    "BasePriceModifier": 1,
    "ConsumableType": "other",
    "Duration": 0,
    "Delay": 0,
    "EffectPeriod": 0,
    "WaitPeriod": 0,
    "Strength": 0,
    "TunnelVisionStrength": 0,
    "CanBeUsedInRaid": true,
    "ItemID": "66d6708ae974feef81150037"
  },
  "66d670dc60343990107f8596": {
    "$type": "RealismMod.Consumable, RealismMod",
    "Name": "Peach Four Loko",
    "TemplateType": "consumable",
    "LoyaltyLevel": 1,
    "BasePriceModifier": 1,
    "ConsumableType": "other",
    "Duration": 0,
    "Delay": 0,
    "EffectPeriod": 0,
    "WaitPeriod": 0,
    "Strength": 0,
    "TunnelVisionStrength": 0,
    "CanBeUsedInRaid": true,
    "ItemID": "66d670dc60343990107f8596"
  },
  "66d67160c06816935ffd7c3a": {
    "$type": "RealismMod.Consumable, RealismMod",
    "Name": "Grape Four Loko",
    "TemplateType": "consumable",
    "LoyaltyLevel": 1,
    "BasePriceModifier": 1,
    "ConsumableType": "other",
    "Duration": 0,
    "Delay": 0,
    "EffectPeriod": 0,
    "WaitPeriod": 0,
    "Strength": 0,
    "TunnelVisionStrength": 0,
    "CanBeUsedInRaid": true,
    "ItemID": "66d67160c06816935ffd7c3a"
  },
  "66d6719af77b8afdcb33671d": {
    "$type": "RealismMod.Consumable, RealismMod",
    "Name": "Fruit Punch Four Loko",
    "TemplateType": "consumable",
    "LoyaltyLevel": 1,
    "BasePriceModifier": 1,
    "ConsumableType": "other",
    "Duration": 0,
    "Delay": 0,
    "EffectPeriod": 0,
    "WaitPeriod": 0,
    "Strength": 0,
    "TunnelVisionStrength": 0,
    "CanBeUsedInRaid": true,
    "ItemID": "66d6719af77b8afdcb33671d"
  },
  "66d671b5129b17aa1a2c4ef4": {
    "$type": "RealismMod.Consumable, RealismMod",
    "Name": "Strawberry Lemonade Four Loko",
    "TemplateType": "consumable",
    "LoyaltyLevel": 1,
    "BasePriceModifier": 1,
    "ConsumableType": "other",
    "Duration": 0,
    "Delay": 0,
    "EffectPeriod": 0,
    "WaitPeriod": 0,
    "Strength": 0,
    "TunnelVisionStrength": 0,
    "CanBeUsedInRaid": true,
    "ItemID": "66d671b5129b17aa1a2c4ef4"
  },
  "66d672114797ef093ace89cd": {
    "$type": "RealismMod.Consumable, RealismMod",
    "Name": "Lemonade Four Loko",
    "TemplateType": "consumable",
    "LoyaltyLevel": 1,
    "BasePriceModifier": 1,
    "ConsumableType": "other",
    "Duration": 0,
    "Delay": 0,
    "EffectPeriod": 0,
    "WaitPeriod": 0,
    "Strength": 0,
    "TunnelVisionStrength": 0,
    "CanBeUsedInRaid": true,
    "ItemID": "66d672114797ef093ace89cd"
  },
  "66d6724a2d614534afc673ca": {
    "$type": "RealismMod.Consumable, RealismMod",
    "Name": "Mango Four Loko",
    "TemplateType": "consumable",
    "LoyaltyLevel": 1,
    "BasePriceModifier": 1,
    "ConsumableType": "other",
    "Duration": 0,
    "Delay": 0,
    "EffectPeriod": 0,
    "WaitPeriod": 0,
    "Strength": 0,
    "TunnelVisionStrength": 0,
    "CanBeUsedInRaid": true,
    "ItemID": "66d6724a2d614534afc673ca"
  },
  "68301e495101b8e85725a5bd": {
    "$type": "RealismMod.Consumable, RealismMod",
    "Name": "Black Cherry Four Loko",
    "TemplateType": "consumable",
    "LoyaltyLevel": 1,
    "BasePriceModifier": 1,
    "ConsumableType": "other",
    "Duration": 0,
    "Delay": 0,
    "EffectPeriod": 0,
    "WaitPeriod": 0,
    "Strength": 0,
    "TunnelVisionStrength": 0,
    "CanBeUsedInRaid": true,
    "ItemID": "68301e495101b8e85725a5bd"
  },
  "683020897a1984bc86e014e9": {
    "$type": "RealismMod.Consumable, RealismMod",
    "Name": "Sour Melon Four Loko",
    "TemplateType": "consumable",
    "LoyaltyLevel": 1,
    "BasePriceModifier": 1,
    "ConsumableType": "other",
    "Duration": 0,
    "Delay": 0,
    "EffectPeriod": 0,
    "WaitPeriod": 0,
    "Strength": 0,
    "TunnelVisionStrength": 0,
    "CanBeUsedInRaid": true,
    "ItemID": "683020897a1984bc86e014e9"
  },
  "683022ff5fd925a8327e42c0": {
    "$type": "RealismMod.Consumable, RealismMod",
    "Name": "Sour Apple Four Loko",
    "TemplateType": "consumable",
    "LoyaltyLevel": 1,
    "BasePriceModifier": 1,
    "ConsumableType": "other",
    "Duration": 0,
    "Delay": 0,
    "EffectPeriod": 0,
    "WaitPeriod": 0,
    "Strength": 0,
    "TunnelVisionStrength": 0,
    "CanBeUsedInRaid": true,
    "ItemID": "683022ff5fd925a8327e42c0"
  },
  "6830243106b81cc888494d1c": {
    "$type": "RealismMod.Consumable, RealismMod",
    "Name": "Margarita Four Loko",
    "TemplateType": "consumable",
    "LoyaltyLevel": 1,
    "BasePriceModifier": 1,
    "ConsumableType": "other",
    "Duration": 0,
    "Delay": 0,
    "EffectPeriod": 0,
    "WaitPeriod": 0,
    "Strength": 0,
    "TunnelVisionStrength": 0,
    "CanBeUsedInRaid": true,
    "ItemID": "6830243106b81cc888494d1c"
  },
  "683024f6fac28eb32fdf9d7c": {
    "$type": "RealismMod.Consumable, RealismMod",
    "Name": "Four Loko Red",
    "TemplateType": "consumable",
    "LoyaltyLevel": 1,
    "BasePriceModifier": 1,
    "ConsumableType": "other",
    "Duration": 0,
    "Delay": 0,
    "EffectPeriod": 0,
    "WaitPeriod": 0,
    "Strength": 0,
    "TunnelVisionStrength": 0,
    "CanBeUsedInRaid": true,
    "ItemID": "683024f6fac28eb32fdf9d7c"
  },
  "683025c0600c37a6b8f5d337": {
    "$type": "RealismMod.Consumable, RealismMod",
    "Name": "Sour Galactic Punch Four Loko",
    "TemplateType": "consumable",
    "LoyaltyLevel": 1,
    "BasePriceModifier": 1,
    "ConsumableType": "other",
    "Duration": 0,
    "Delay": 0,
    "EffectPeriod": 0,
    "WaitPeriod": 0,
    "Strength": 0,
    "TunnelVisionStrength": 0,
    "CanBeUsedInRaid": true,
    "ItemID": "683025c0600c37a6b8f5d337"
  },
  "683026d32570c28259f7c77e": {
    "$type": "RealismMod.Consumable, RealismMod",
    "Name": "Four Loko Gold",
    "TemplateType": "consumable",
    "LoyaltyLevel": 1,
    "BasePriceModifier": 1,
    "ConsumableType": "other",
    "Duration": 0,
    "Delay": 0,
    "EffectPeriod": 0,
    "WaitPeriod": 0,
    "Strength": 0,
    "TunnelVisionStrength": 0,
    "CanBeUsedInRaid": true,
    "ItemID": "683026d32570c28259f7c77e"
  },
  "6830271ac5628c92cf9a6f0b": {
    "$type": "RealismMod.Consumable, RealismMod",
    "Name": "Four Loko Bold: Blaze",
    "TemplateType": "consumable",
    "LoyaltyLevel": 1,
    "BasePriceModifier": 1,
    "ConsumableType": "other",
    "Duration": 0,
    "Delay": 0,
    "EffectPeriod": 0,
    "WaitPeriod": 0,
    "Strength": 0,
    "TunnelVisionStrength": 0,
    "CanBeUsedInRaid": true,
    "ItemID": "6830271ac5628c92cf9a6f0b"
  },
  "68302864c2c90f1024ee4779": {
    "$type": "RealismMod.Consumable, RealismMod",
    "Name": "Four Loko Bold: Frost",
    "TemplateType": "consumable",
    "LoyaltyLevel": 1,
    "BasePriceModifier": 1,
    "ConsumableType": "other",
    "Duration": 0,
    "Delay": 0,
    "EffectPeriod": 0,
    "WaitPeriod": 0,
    "Strength": 0,
    "TunnelVisionStrength": 0,
    "CanBeUsedInRaid": true,
    "ItemID": "68302864c2c90f1024ee4779"
  },
  "683028f8de12b685fc244737": {
    "$type": "RealismMod.Consumable, RealismMod",
    "Name": "Four Loko Bold: Storm",
    "TemplateType": "consumable",
    "LoyaltyLevel": 1,
    "BasePriceModifier": 1,
    "ConsumableType": "other",
    "Duration": 0,
    "Delay": 0,
    "EffectPeriod": 0,
    "WaitPeriod": 0,
    "Strength": 0,
    "TunnelVisionStrength": 0,
    "CanBeUsedInRaid": true,
    "ItemID": "683028f8de12b685fc244737"
  }
}